plotGeneratorPL/__init__.py
plotGeneratorPL/imageJ_tool.py
plotGeneratorPL/main.py
plotGeneratorPL/plot_FTIR.py
plotGeneratorPL/utils.py
plotGeneratorPL-1.2.dist-info/LICENSE
plotGeneratorPL-1.2.dist-info/METADATA
plotGeneratorPL-1.2.dist-info/WHEEL
plotGeneratorPL-1.2.dist-info/entry_points.txt
plotGeneratorPL-1.2.dist-info/top_level.txt
plotGeneratorPL-1.2.dist-info/RECORD
