Metadata-Version: 2.1
Name: plotGeneratorPL
Version: 1.2
Summary: A package for processing and plotting images
Author-email: PiceaLiu <picealiu@uw.edu>
License: MIT
Classifier: Programming Language :: Python :: 3
Classifier: License :: OSI Approved :: MIT License
Classifier: Operating System :: OS Independent
Requires-Python: <4,>=3.7
License-File: LICENSE
Requires-Dist: numpy<2
Requires-Dist: pandas>=2.0
Requires-Dist: matplotlib>=3.4.3
Requires-Dist: openpyxl>=3.1
Requires-Dist: opencv-python>=4.5.3.56
Requires-Dist: streamlit==1.32.0
Requires-Dist: libroadrunner==2.7.0
Requires-Dist: numba>=0.59.1
Requires-Dist: pywavelets>=1.5.0
